xtb-22.1.dist-info/RECORD
xtb-22.1.dist-info/METADATA
xtb-22.1.dist-info/WHEEL
xtb.libs/libgfortran-030428ab.so.5.0.0
xtb.libs/libmctc-lib-88ae979e.so.0.3.1
xtb.libs/libopenblasp-r0-8da378a1.3.21.so
xtb.libs/libgomp-38ea1071.so.1.0.0
xtb.libs/libxtb-6b591d86.so.6.5.1
xtb.libs/libquadmath-80ef4a46.so.0.0.0
xtb/_libxtb.cpython-311-x86_64-linux-gnu.so
xtb-22.1.data/purelib/xtb/interface.py
xtb-22.1.data/purelib/xtb/__init__.py
xtb-22.1.data/purelib/xtb/libxtb.py
xtb-22.1.data/purelib/xtb/test_utils.py
xtb-22.1.data/purelib/xtb/test_libxtb.py
xtb-22.1.data/purelib/xtb/utils.py
xtb-22.1.data/purelib/xtb/test_interface.py
xtb-22.1.data/purelib/xtb/qcschema/__init__.py
xtb-22.1.data/purelib/xtb/qcschema/test_qcschema.py
xtb-22.1.data/purelib/xtb/qcschema/harness.py
xtb-22.1.data/purelib/xtb/ase/__init__.py
xtb-22.1.data/purelib/xtb/ase/calculator.py
xtb-22.1.data/purelib/xtb/ase/test_calculator.py
xtb-22.1.data/purelib/xtb/ase/test_optimize.py
