Metadata-Version: 2.1
Name: xtb
Version: 22.1
Summary: Python API for the extended tight-binding program
License: LGPL-3.0-or-later
Classifier: Intended Audience :: Science/Research
Classifier: Programming Language :: Fortran
Classifier: Programming Language :: Python :: 3
Classifier: Programming Language :: Python :: 3.6
Classifier: Programming Language :: Python :: 3.7
Classifier: Programming Language :: Python :: 3.8
Classifier: Programming Language :: Python :: 3.9
Classifier: Programming Language :: Python :: 3.10
Classifier: Programming Language :: Python :: 3.11
Classifier: Topic :: Scientific/Engineering :: Chemistry
Classifier: Topic :: Scientific/Engineering :: Physics
Project-URL: Repository, https://github.com/grimme-lab/xtb-python
Project-URL: Documentation, https://xtb-python.readthedocs.io
Requires-Python: >=3.7
Requires-Dist: cffi
Requires-Dist: numpy
Requires-Dist: ase; extra == "ase"
Requires-Dist: qcelemental; extra == "qcschema"
Requires-Dist: pytest; extra == "test"
Requires-Dist: pytest-cov; extra == "test"
Requires-Dist: ase; extra == "test"
Requires-Dist: qcelemental; extra == "test"
Provides-Extra: ase
Provides-Extra: qcschema
Provides-Extra: test
